nektar/__init__.py
nektar/appbase.py
nektar/base58.py
nektar/condenser.py
nektar/constants.py
nektar/mock.py
nektar/nektar.py
nektar/transactions.py
nektar/utils.py
hive_nektar-1.1.7.dist-info/WHEEL
hive_nektar-1.1.7.dist-info/METADATA
hive_nektar-1.1.7.dist-info/licenses/LICENSE.txt
hive_nektar-1.1.7.dist-info/RECORD
