Metadata-Version: 2.1
Name: hive-nektar
Version: 1.1.7
Summary: Nektar, Hive API SDK for Python
License: LICENSE.txt
Keywords: nektar,hive,blockchain,api,sdk
Author: Rodney Maniego Jr.
Author-email: rodney.maniegojr@gmail.com
Requires-Python: >=3.10
Classifier: Development Status :: 5 - Production/Stable
Classifier: Intended Audience :: Developers
Classifier: License :: OSI Approved :: MIT License
Classifier: Programming Language :: Python :: 3
Classifier: Topic :: Software Development :: Build Tools
Requires-Dist: ecdsa
Requires-Dist: requests
Project-URL: documentation, https://nektar.readthedocs.io
Project-URL: homepage, https://github.com/rmaniego/nektar
